extra_pydantic/__init__.py
extra_pydantic/fields.py
extra_pydantic/main.py
extra_pydantic/monkeypatch.py
extra_pydantic/py.typed
extra_pydantic/validators.py
extra_pydantic-0.1.0.dist-info/LICENSE
extra_pydantic-0.1.0.dist-info/METADATA
extra_pydantic-0.1.0.dist-info/WHEEL
extra_pydantic-0.1.0.dist-info/top_level.txt
extra_pydantic-0.1.0.dist-info/RECORD
